MANIFEST.in
README.rst
setup.py
django_icons_onebit.egg-info/PKG-INFO
django_icons_onebit.egg-info/SOURCES.txt
django_icons_onebit.egg-info/dependency_links.txt
django_icons_onebit.egg-info/requires.txt
django_icons_onebit.egg-info/top_level.txt
icons_onebit/__init__.py
icons_onebit/models.py
icons_onebit/static/icons/.noremove
icons_onebit/static/icons/onebit/1/preview.jpg
icons_onebit/static/icons/onebit/1/readme.txt
icons_onebit/static/icons/onebit/1/PNG/onebit_01.png
icons_onebit/static/icons/onebit/1/PNG/onebit_02.png
icons_onebit/static/icons/onebit/1/PNG/onebit_03.png
icons_onebit/static/icons/onebit/1/PNG/onebit_04.png
icons_onebit/static/icons/onebit/1/PNG/onebit_05.png
icons_onebit/static/icons/onebit/1/PNG/onebit_06.png
icons_onebit/static/icons/onebit/1/PNG/onebit_07.png
icons_onebit/static/icons/onebit/1/PNG/onebit_08.png
icons_onebit/static/icons/onebit/1/PNG/onebit_09.png
icons_onebit/static/icons/onebit/1/PNG/onebit_10.png
icons_onebit/static/icons/onebit/1/PNG/onebit_11.png
icons_onebit/static/icons/onebit/1/PNG/onebit_12.png
icons_onebit/static/icons/onebit/1/PNG/onebit_13.png
icons_onebit/static/icons/onebit/1/PNG/onebit_14.png
icons_onebit/static/icons/onebit/1/PNG/onebit_15.png
icons_onebit/static/icons/onebit/1/PNG/onebit_16.png
icons_onebit/static/icons/onebit/1/PNG/onebit_17.png
icons_onebit/static/icons/onebit/1/PNG/onebit_18.png
icons_onebit/static/icons/onebit/1/PNG/onebit_19.png
icons_onebit/static/icons/onebit/1/PNG/onebit_20.png
icons_onebit/static/icons/onebit/1/PNG/onebit_21.png
icons_onebit/static/icons/onebit/1/PNG/onebit_22.png
icons_onebit/static/icons/onebit/1/PNG/onebit_23.png
icons_onebit/static/icons/onebit/1/PNG/onebit_24.png
icons_onebit/static/icons/onebit/1/PNG/onebit_25.png
icons_onebit/static/icons/onebit/1/PNG/onebit_26.png
icons_onebit/static/icons/onebit/1/PNG/onebit_27.png
icons_onebit/static/icons/onebit/1/PNG/onebit_28.png
icons_onebit/static/icons/onebit/1/PNG/onebit_29.png
icons_onebit/static/icons/onebit/1/PNG/onebit_30.png
icons_onebit/static/icons/onebit/1/PNG/onebit_31.png
icons_onebit/static/icons/onebit/1/PNG/onebit_32.png
icons_onebit/static/icons/onebit/1/PNG/onebit_33.png
